persisdict/__init__.py
persisdict/persisdict.py
persisdict-1.0.dist-info/LICENSE
persisdict-1.0.dist-info/METADATA
persisdict-1.0.dist-info/WHEEL
persisdict-1.0.dist-info/top_level.txt
persisdict-1.0.dist-info/RECORD
