Metadata-Version: 2.1
Name: persisdict
Version: 1.0
Summary: A package for simple state management
Home-page: http://github.com/secsandcyber/persisdict
Author: Matthew Molyett
Author-email: matthewmolyett@gmail.com
License: UNKNOWN
Platform: UNKNOWN
